<?xml version="1.0" encoding="utf-8"?>
<extension method="upgrade" type="component" version="2.5.0">
    <name>COM_CMC</name>
    <author>Compojoom.com</author>
    <creationDate>@@DATE@@</creationDate>
    <copyright>(C) 2013 - compojoom.com</copyright>
    <authorEmail>contact-us@compojoom.com</authorEmail>
    <authorUrl>www.compojoom.com</authorUrl>
    <version>@@VERSION@@</version>
    <license>http://www.gnu.org/copyleft/gpl.html GNU/GPL</license>
    <description><![CDATA[Mailchimp list management for Joomla!]]></description>
    <scriptfile>script.php</scriptfile>
    <files folder="components/com_cmc">
        ##FRONTENDCOMPONENTPACKAGEFILES##
    </files>
    <languages folder="language">
        ##FRONTENDLANGUAGEFILES##
    </languages>
    <administration>
        <menu img="../media/com_cmc/backend/images/cmc-16px.png" view="cpanel">COM_CMC</menu>
        <submenu>
            <menu img="../media/com_cmc/backend/images/lists-16px.png" view="lists">COM_CMC_LISTS</menu>
            <menu img="../media/com_cmc/backend/images/users-16px.png" view="users">COM_CMC_USERS</menu>
        </submenu>
        <files folder="administrator/components/com_cmc">
            ##ADMINCOMPONENTPACKAGEFILES##
        </files>
        <languages folder="administrator/language">
            ##ADMINLANGUAGEFILES##
        </languages>
    </administration>
    <media destination="com_@@COMPONENTNAME@@" folder="media/com_cmc">
        ##MEDIAPACKAGEFILES##
    </media>

    <updateservers>
        <server type="extension" priority="1" name="CMC Updates"><![CDATA[https://compojoom.com/index.php?option=com_ars&view=update&task=stream&format=xml&id=13&dummy=extension.xml]]></server>
    </updateservers>
</extension>